artlib/__init__.py
artlib/biclustering/BARTMAP.py
artlib/biclustering/__init__.py
artlib/common/BaseART.py
artlib/common/BaseARTMAP.py
artlib/common/VAT.py
artlib/common/__init__.py
artlib/common/utils.py
artlib/common/visualization.py
artlib/cvi/CVIART.py
artlib/cvi/__init__.py
artlib/cvi/iCVIFuzzyArt.py
artlib/cvi/iCVIs/CalinkskiHarabasz.py
artlib/cvi/iCVIs/__init__.py
artlib/elementary/ART1.py
artlib/elementary/ART2.py
artlib/elementary/BayesianART.py
artlib/elementary/BinaryFuzzyART.py
artlib/elementary/EllipsoidART.py
artlib/elementary/FuzzyART.py
artlib/elementary/GaussianART.py
artlib/elementary/HypersphereART.py
artlib/elementary/QuadraticNeuronART.py
artlib/elementary/__init__.py
artlib/experimental/AlphaART.py
artlib/experimental/SeqART.py
artlib/experimental/SphericalAlphaART.py
artlib/experimental/__init__.py
artlib/experimental/merging.py
artlib/fusion/FusionART.py
artlib/fusion/__init__.py
artlib/hierarchical/DeepARTMAP.py
artlib/hierarchical/SMART.py
artlib/hierarchical/__init__.py
artlib/optimized/BinaryFuzzyARTMAPFactory.py
artlib/optimized/FuzzyARTMAPFactory.py
artlib/optimized/GaussianARTMAPFactory.py
artlib/optimized/HypersphereARTMAPFactory.py
artlib/optimized/__init__.py
artlib/optimized/backends/__init__.py
artlib/optimized/backends/cpp/BinaryFuzzyARTMAP.py
artlib/optimized/backends/cpp/FuzzyARTMAP.py
artlib/optimized/backends/cpp/GaussianARTMAP.py
artlib/optimized/backends/cpp/HypersphereARTMAP.py
artlib/optimized/backends/cpp/__init__.py
artlib/optimized/backends/cpp/cppBinaryFuzzyARTMAP.cpp
artlib/optimized/backends/cpp/cppBinaryFuzzyARTMAP.cpython-314t-x86_64-linux-musl.so
artlib/optimized/backends/cpp/cppFuzzyARTMAP.cpp
artlib/optimized/backends/cpp/cppFuzzyARTMAP.cpython-314t-x86_64-linux-musl.so
artlib/optimized/backends/cpp/cppGaussianARTMAP.cpp
artlib/optimized/backends/cpp/cppGaussianARTMAP.cpython-314t-x86_64-linux-musl.so
artlib/optimized/backends/cpp/cppHypersphereARTMAP.cpp
artlib-0.1.7.dist-info/METADATA
artlib-0.1.7.dist-info/WHEEL
artlib-0.1.7.dist-info/top_level.txt
artlib-0.1.7.dist-info/RECORD
artlib-0.1.7.dist-info/licenses/LICENSE
