Metadata-Version: 2.4
Name: artlib
Version: 0.1.7
Summary: A Python library for Adaptive Resonance Theory (ART) algorithms.
Requires-Python: >=3.9
License-File: LICENSE
Dynamic: license-file
